reminix_runtime/__init__.py
reminix_runtime/agent.py
reminix_runtime/agent_adapter.py
reminix_runtime/content.py
reminix_runtime/py.typed
reminix_runtime/server.py
reminix_runtime/tool.py
reminix_runtime/types.py
reminix_runtime-0.0.18.dist-info/METADATA
reminix_runtime-0.0.18.dist-info/WHEEL
reminix_runtime-0.0.18.dist-info/licenses/LICENSE
reminix_runtime-0.0.18.dist-info/RECORD
